LICENSE
MANIFEST.in
README.rst
setup.py
isodatetimehandler/__init__.py
isodatetimehandler.egg-info/PKG-INFO
isodatetimehandler.egg-info/SOURCES.txt
isodatetimehandler.egg-info/dependency_links.txt
isodatetimehandler.egg-info/top_level.txt