Metadata-Version: 1.0
Name: isodatetimehandler
Version: 1.0.1
Summary: An alternate jsonpickle handler for datetime objects.
Home-page: https://github.com/fictorial/jsonpickle-isodatetimehandler
Author: Brian Hammond
Author-email: brian@fictorial.com
License: The MIT License (MIT)
